PirxcyPinger/__init__.py
PirxcyPinger/exceptions.py
PirxcyPinger/extensions.py
PirxcyPinger-5.0.0.dist-info/METADATA
PirxcyPinger-5.0.0.dist-info/WHEEL
PirxcyPinger-5.0.0.dist-info/top_level.txt
PirxcyPinger-5.0.0.dist-info/RECORD
