Metadata-Version: 2.1
Name: PirxcyPinger
Version: 5.0.0
Summary: Async Tool For Uploading URL's To PirxcyPinger
Home-page: https://pirxcypingerfinal.pirxcy1942.repl.co/
Author: Pirxcy
License: UNKNOWN
Platform: UNKNOWN
Classifier: Programming Language :: Python :: 3
Classifier: License :: OSI Approved :: MIT License
Classifier: Operating System :: OS Independent
Requires-Dist: aiohttp
